liara/__init__.py
liara/actions.py
liara/cache.py
liara/cmdline.py
liara/config.py
liara/feeds.py
liara/md.py
liara/nodes.py
liara/publish.py
liara/query.py
liara/quickstart.py
liara/server.py
liara/signals.py
liara/site.py
liara/template.py
liara/tools.py
liara/util.py
liara/yaml.py
liara/plugins/__init__.py
liara/plugins/has_pending_document.py
liara/plugins/series_schedule.py
liara/static/nodes.jinja2
liara-2.7.3.dist-info/METADATA
liara-2.7.3.dist-info/WHEEL
liara-2.7.3.dist-info/entry_points.txt
liara-2.7.3.dist-info/licenses/LICENSE.txt
liara-2.7.3.dist-info/RECORD
