Metadata-Version: 2.4
Name: Liara
Version: 2.7.3
Summary: Liara is a static page generator
Project-URL: Homepage, https://liara.sh13.net
Project-URL: Issue Tracker, https://github.com/anteru/liara/issues
Project-URL: Repository, https://github.com/anteru/liara
Project-URL: Documentation, https://liara-web.readthedocs.io
Author-email: "Matthäus G. Chajdas" <dev@anteru.net>
License: BSD 2-clause license
License-File: LICENSE.txt
Keywords: ssg,static site generator,static sites
Classifier: Development Status :: 5 - Production/Stable
Classifier: Environment :: Console
Classifier: Intended Audience :: End Users/Desktop
Classifier: License :: OSI Approved :: BSD License
Classifier: Natural Language :: English
Classifier: Operating System :: OS Independent
Classifier: Programming Language :: Python :: 3
Classifier: Programming Language :: Python :: 3.10
Classifier: Programming Language :: Python :: 3.11
Classifier: Programming Language :: Python :: 3.12
Classifier: Topic :: Internet :: WWW/HTTP :: Dynamic Content :: Content Management System
Requires-Python: >=3.10
Requires-Dist: beautifulsoup4~=4.12
Requires-Dist: blinker~=1.7
Requires-Dist: click~=8.1
Requires-Dist: dateparser~=1.2
Requires-Dist: humanfriendly~=10.0
Requires-Dist: jinja2~=3.1
Requires-Dist: libsass~=0.21
Requires-Dist: lxml~=6.0
Requires-Dist: mako~=1.3
Requires-Dist: markdown~=3.5
Requires-Dist: pillow~=12.0
Requires-Dist: pygments~=2.18
Requires-Dist: pymdown-extensions~=10.0
Requires-Dist: python-slugify~=8.0
Requires-Dist: pyyaml~=6.0
Requires-Dist: requests~=2.31
Requires-Dist: tomli~=2.0; python_version < '3.11'
Requires-Dist: tzlocal~=5.2
Requires-Dist: watchfiles~=1.0
Provides-Extra: compression
Requires-Dist: brotli~=1.2.0; extra == 'compression'
Requires-Dist: zstd~=1.5.7.2; extra == 'compression'
Provides-Extra: dev
Requires-Dist: flake8; extra == 'dev'
Requires-Dist: flake8-mypy; extra == 'dev'
Requires-Dist: tox; extra == 'dev'
Provides-Extra: docs
Requires-Dist: furo; extra == 'docs'
Requires-Dist: sphinx-autodoc2; extra == 'docs'
Requires-Dist: sphinx~=8.0; extra == 'docs'
Provides-Extra: redis
Requires-Dist: redis~=5.0; extra == 'redis'
